snmpfwd/__init__.py
snmpfwd/cparser.py
snmpfwd/daemon.py
snmpfwd/endpoint.py
snmpfwd/error.py
snmpfwd/lazylog.py
snmpfwd/log.py
snmpfwd/macro.py
snmpfwd/next.py
snmpfwd/plugins/__init__.py
snmpfwd/plugins/manager.py
snmpfwd/plugins/status.py
snmpfwd/scripts/snmpfwdclient.py
snmpfwd/scripts/snmpfwdserver.py
snmpfwd/trunking/__init__.py
snmpfwd/trunking/client.py
snmpfwd/trunking/crypto.py
snmpfwd/trunking/endpoint.py
snmpfwd/trunking/manager.py
snmpfwd/trunking/protocol.py
snmpfwd/trunking/server.py
snmpfwd_lextudio-0.4.4.dist-info/entry_points.txt
snmpfwd_lextudio-0.4.4.dist-info/LICENSE.txt
snmpfwd_lextudio-0.4.4.dist-info/WHEEL
snmpfwd_lextudio-0.4.4.dist-info/METADATA
snmpfwd_lextudio-0.4.4.dist-info/RECORD
