Metadata-Version: 2.1
Name: snmpfwd-lextudio
Version: 0.4.4
Summary: SNMP Proxy Forwarder can act as an application-level firewall or SNMP protocol translator that let SNMPv1/v2c entities to talk to SNMPv3 ones or vice-versa.
Home-page: https://github.com/lextudio/snmpfwd
License: BSD-2-Clause
Author: Lex Li
Author-email: support@lextudio.com
Requires-Python: >=3.7,<4.0
Classifier: Development Status :: 5 - Production/Stable
Classifier: Environment :: Console
Classifier: Intended Audience :: Developers
Classifier: Intended Audience :: Education
Classifier: Intended Audience :: Information Technology
Classifier: Intended Audience :: System Administrators
Classifier: Intended Audience :: Telecommunications Industry
Classifier: License :: OSI Approved :: BSD License
Classifier: Natural Language :: English
Classifier: Operating System :: OS Independent
Classifier: Programming Language :: Python :: 3
Classifier: Programming Language :: Python :: 3.7
Classifier: Programming Language :: Python :: 3.8
Classifier: Programming Language :: Python :: 3.9
Classifier: Programming Language :: Python :: 3.10
Classifier: Programming Language :: Python :: 3.11
Classifier: Topic :: Communications
Classifier: Topic :: System :: Monitoring
Classifier: Topic :: System :: Networking :: Monitoring
Requires-Dist: pycryptodomex (>=3.11.0,<4.0.0)
Requires-Dist: pysnmp-lextudio (>=4.4.3)
Project-URL: Repository, https://github.com/lextudio/snmpfwd
